cdfm/__init__.py
cdfm/config.py
cdfm/consts.py
cdfm/data.py
cdfm/measures.py
cdfm/testing.py
cdfm/types.py
cdfm/utils.py
cdfm/models/__init__.py
cdfm/models/base.py
cdfm/models/differentials.py
cdfm/models/equations.py
cdfm/models/rankers.py
tests/__init__.py
tests/test_measures.py
tests/test_utils.py
tests/models/__init__.py
tests/models/test_differentials.py
tests/models/test_equations.py
tests/models/test_rankers.py
cdfm-0.0.1.dist-info/LICENSE
cdfm-0.0.1.dist-info/METADATA
cdfm-0.0.1.dist-info/WHEEL
cdfm-0.0.1.dist-info/top_level.txt
cdfm-0.0.1.dist-info/RECORD
